core/__init__.py
core/agent/__init__.py
core/agent/base.py
core/agent/rag.py
core/agent/research.py
core/base/__init__.py
core/base/abstractions/__init__.py
core/base/agent/__init__.py
core/base/agent/agent.py
core/base/agent/tools/registry.py
core/base/agent/tools/built_in/get_file_content.py
core/base/agent/tools/built_in/search_file_descriptions.py
core/base/agent/tools/built_in/search_file_knowledge.py
core/base/agent/tools/built_in/tavily_extract.py
core/base/agent/tools/built_in/tavily_search.py
core/base/agent/tools/built_in/web_scrape.py
core/base/agent/tools/built_in/web_search.py
core/base/api/models/__init__.py
core/base/parsers/__init__.py
core/base/parsers/base_parser.py
core/base/providers/__init__.py
core/base/providers/auth.py
core/base/providers/base.py
core/base/providers/crypto.py
core/base/providers/database.py
core/base/providers/email.py
core/base/providers/embedding.py
core/base/providers/file.py
core/base/providers/ingestion.py
core/base/providers/llm.py
core/base/providers/ocr.py
core/base/providers/orchestration.py
core/base/providers/scheduler.py
core/base/utils/__init__.py
core/configs/full.toml
core/configs/full_azure.toml
core/configs/full_lm_studio.toml
core/configs/full_ollama.toml
core/configs/gemini.toml
core/configs/lm_studio.toml
core/configs/ollama.toml
core/configs/r2r_azure.toml
core/configs/r2r_azure_with_test_limits.toml
core/configs/r2r_with_auth.toml
core/configs/tavily.toml
core/examples/__init__.py
core/examples/hello_r2r.py
core/examples/supported_file_types/py.py
core/main/__init__.py
core/main/abstractions.py
core/main/app.py
core/main/app_entry.py
core/main/config.py
core/main/api/v3/base_router.py
core/main/api/v3/chunks_router.py
core/main/api/v3/collections_router.py
core/main/api/v3/conversations_router.py
core/main/api/v3/documents_router.py
core/main/api/v3/graph_router.py
core/main/api/v3/indices_router.py
core/main/api/v3/prompts_router.py
core/main/api/v3/retrieval_router.py
core/main/api/v3/system_router.py
r2r-3.6.6.dist-info/METADATA
r2r-3.6.6.dist-info/WHEEL
r2r-3.6.6.dist-info/entry_points.txt
r2r-3.6.6.dist-info/top_level.txt
r2r-3.6.6.dist-info/RECORD
