Metadata-Version: 2.4
Name: r2r
Version: 3.6.6
Summary: SciPhi R2R
Author-email: Owen Colegrove <owen@sciphi.ai>
License: MIT
Requires-Python: <3.13,>=3.10
Requires-Dist: aiofiles<25.0.0,>=24.1.0
Requires-Dist: alembic<2.0.0,>=1.13.3
Requires-Dist: fastapi<0.116.0,>=0.115.11
Requires-Dist: httpx>=0.27.0
Requires-Dist: openai>=1.99.0
Requires-Dist: python-dotenv<2.0.0,>=1.0.1
Requires-Dist: psycopg-binary<4.0.0,>=3.2.3
Requires-Dist: requests<3.0.0,>=2.31.0
Requires-Dist: tiktoken<0.9.0,>=0.8.0
Requires-Dist: toml<0.11.0,>=0.10.2
Requires-Dist: types-requests<3.0.0,>=2.31.0
Requires-Dist: types-aiofiles<25.0.0,>=24.1.0.20240626
Requires-Dist: typing-extensions<5.0.0,>=4.12.2
Requires-Dist: pydantic>=2.10.6
Requires-Dist: python-json-logger>=3.2.1
Requires-Dist: filetype>=1.2.0
Provides-Extra: core
Requires-Dist: aiohttp<4.0.0,>=3.10.10; extra == "core"
Requires-Dist: aioshutil<2.0,>=1.5; extra == "core"
Requires-Dist: aiosqlite<0.21.0,>=0.20.0; extra == "core"
Requires-Dist: anthropic>=0.49.0; extra == "core"
Requires-Dist: apscheduler<4.0.0,>=3.10.4; extra == "core"
Requires-Dist: asyncpg<0.30.0,>=0.29.0; extra == "core"
Requires-Dist: azure-ai-inference<2.0.0,>=1.0.0b8; extra == "core"
Requires-Dist: azure-ai-ml<2.0.0,>=1.24.0; extra == "core"
Requires-Dist: bcrypt<5.0.0,>=4.1.3; extra == "core"
Requires-Dist: beautifulsoup4<5.0.0,>=4.12.3; extra == "core"
Requires-Dist: boto3<2.0.0,>=1.35.17; extra == "core"
Requires-Dist: colorlog<7.0.0,>=6.9.0; extra == "core"
Requires-Dist: docutils<0.22.0,>=0.21.2; extra == "core"
Requires-Dist: epub<0.6.0,>=0.5.2; extra == "core"
Requires-Dist: firecrawl-py>=1.13.5; extra == "core"
Requires-Dist: fsspec<2025.0.0,>=2024.6.0; extra == "core"
Requires-Dist: future<2.0.0,>=1.0.0; extra == "core"
Requires-Dist: google-auth<3.0.0,>=2.37.0; extra == "core"
Requires-Dist: google-auth-oauthlib<2.0.0,>=1.2.1; extra == "core"
Requires-Dist: google-genai<0.7.0,>=0.6.0; extra == "core"
Requires-Dist: gunicorn<22.0.0,>=21.2.0; extra == "core"
Requires-Dist: hatchet-sdk==0.47.0; extra == "core"
Requires-Dist: litellm>=1.69.3; extra == "core"
Requires-Dist: markdown<4.0,>=3.6; extra == "core"
Requires-Dist: mistralai>=1.5.2; extra == "core"
Requires-Dist: msg-parser>=1.2.0; extra == "core"
Requires-Dist: networkx<4.0,>=3.3; extra == "core"
Requires-Dist: numpy<1.29.0,>=1.22.4; extra == "core"
Requires-Dist: olefile<0.48,>=0.47; extra == "core"
Requires-Dist: ollama<0.4.0,>=0.3.1; extra == "core"
Requires-Dist: openpyxl<4.0.0,>=3.1.2; extra == "core"
Requires-Dist: orgparse<0.5.0,>=0.4.20231004; extra == "core"
Requires-Dist: pdf2image>=1.17.0; extra == "core"
Requires-Dist: pillow<12.0.0,>=11.1.0; extra == "core"
Requires-Dist: pillow-heif<0.22.0,>=0.21.0; extra == "core"
Requires-Dist: psutil<7.0.0,>=6.0.0; extra == "core"
Requires-Dist: pydantic[email]<3.0.0,>=2.8.2; extra == "core"
Requires-Dist: pyjwt<3.0.0,>=2.8.0; extra == "core"
Requires-Dist: pynacl<2.0.0,>=1.5.0; extra == "core"
Requires-Dist: pypdf<5.0.0,>=4.2.0; extra == "core"
Requires-Dist: pypdf2<4.0.0,>=3.0.1; extra == "core"
Requires-Dist: python-docx<2.0.0,>=1.1.0; extra == "core"
Requires-Dist: python-multipart<0.0.19,>=0.0.9; extra == "core"
Requires-Dist: python-pptx<2.0.0,>=1.0.1; extra == "core"
Requires-Dist: pyyaml<7.0.0,>=6.0.1; extra == "core"
Requires-Dist: sendgrid<7.0.0,>=6.11.0; extra == "core"
Requires-Dist: mailersend<0.6.0,>=0.5.6; extra == "core"
Requires-Dist: sentry-sdk<3.0.0,>=2.20.0; extra == "core"
Requires-Dist: sqlalchemy<3.0.0,>=2.0.30; extra == "core"
Requires-Dist: striprtf<0.0.29,>=0.0.28; extra == "core"
Requires-Dist: supabase<3.0.0,>=2.15.0; extra == "core"
Requires-Dist: tokenizers==0.19; extra == "core"
Requires-Dist: unstructured-client==0.34.0; extra == "core"
Requires-Dist: uvicorn<0.28.0,>=0.27.0.post1; extra == "core"
Requires-Dist: vecs<0.5.0,>=0.4.0; extra == "core"
Requires-Dist: xlrd<3.0.0,>=2.0.1; extra == "core"
